[{"id":1,"author":"Gare Limpricht","book_name":"Black Book (Zwartboek)","pages":366,"published_year":2017},
{"id":2,"author":"Fielding Victor","book_name":"Nine Lives","pages":401,"published_year":1909},
{"id":3,"author":"Ethel Melody","book_name":"Citizen Koch","pages":343,"published_year":1932},
{"id":4,"author":"Elnora Alenichev","book_name":"Canyon Passage","pages":563,"published_year":1975},
{"id":5,"author":"Ara Layson","book_name":"Big Bang Theory, The (2007-)","pages":276,"published_year":1953},
{"id":6,"author":"Alena Nieass","book_name":"Me and Orson Welles","pages":296,"published_year":1967},
{"id":7,"author":"Farrel Bail","book_name":"Two of a Kind","pages":364,"published_year":1907},
{"id":8,"author":"Jard Moreby","book_name":"Birth","pages":499,"published_year":1916},
{"id":9,"author":"Veronica Cassin","book_name":"Sword and the Dragon, The (Ilya Muromets)","pages":309,"published_year":1950},
{"id":10,"author":"Ramsay Aitkin","book_name":"Open Road, The","pages":471,"published_year":1974},
{"id":11,"author":"Mag Della Scala","book_name":"Bluebeard","pages":401,"published_year":1985},
{"id":12,"author":"Steve Grimston","book_name":"Cool World","pages":431,"published_year":1923},
{"id":13,"author":"Shir Cattlow","book_name":"Whispering Corridors (Yeogo Goedam)","pages":346,"published_year":1987},
{"id":14,"author":"Shanta Jossum","book_name":"Confessor, The (a.k.a. The Good Shepherd)","pages":425,"published_year":1992},
{"id":15,"author":"Karie McAlpine","book_name":"Window, The","pages":205,"published_year":1960},
{"id":16,"author":"Monty Sproston","book_name":"Decoy Bride, The","pages":287,"published_year":1933},
{"id":17,"author":"Massimo Syratt","book_name":"Whirlpool","pages":454,"published_year":1902},
{"id":18,"author":"Louise Manlow","book_name":"Here Without Me (Inja bedoone man)","pages":265,"published_year":1924},
{"id":19,"author":"Magdalene Ohrt","book_name":"Child Is Waiting, A","pages":217,"published_year":1984},
{"id":20,"author":"Hamil Marks","book_name":"Stewart Lee: If You Prefer a Milder Comedian, Please Ask for One","pages":256,"published_year":1983},
{"id":21,"author":"Jamison Andrei","book_name":"The Death and Life of Bobby Z","pages":597,"published_year":1928},
{"id":22,"author":"Rodrique O'Mullally","book_name":"Police Story (Ging chaat goo si)","pages":585,"published_year":1942},
{"id":23,"author":"Gard Egan","book_name":"Blackjack","pages":275,"published_year":1910},
{"id":24,"author":"Alastair Kinchlea","book_name":"Safe Passage","pages":276,"published_year":2003},
{"id":25,"author":"Siegfried Mathwin","book_name":"Au revoir les enfants","pages":427,"published_year":2018},
{"id":26,"author":"Xylina Borgars","book_name":"Lawnmower Man, The","pages":366,"published_year":1913},
{"id":27,"author":"Floris Welsh","book_name":"Miss Météo","pages":495,"published_year":1965},
{"id":28,"author":"Humberto Bidgood","book_name":"Underworld","pages":217,"published_year":1939},
{"id":29,"author":"Fawn Maass","book_name":"Blade, The (Dao)","pages":365,"published_year":1923},
{"id":30,"author":"Gavrielle Element","book_name":"Shooter","pages":547,"published_year":2006},
{"id":31,"author":"Olympie Campelli","book_name":"Single Shot, A","pages":598,"published_year":2012},
{"id":32,"author":"Wynn Goulder","book_name":"Around the Bend","pages":600,"published_year":1982},
{"id":33,"author":"Benedikt Euels","book_name":"Parisienne, La (Une parisienne)","pages":535,"published_year":1972},
{"id":34,"author":"Catha Mayou","book_name":"Sunshine Boys, The","pages":513,"published_year":1914},
{"id":35,"author":"Gilberto Robelin","book_name":"Pulling John","pages":277,"published_year":1902},
{"id":36,"author":"Jacquie Schruur","book_name":"Danger: Diabolik (Diabolik)","pages":247,"published_year":2017},
{"id":37,"author":"Stepha Haygreen","book_name":"Magnum Cop","pages":333,"published_year":2003},
{"id":38,"author":"Glory Methringham","book_name":"Morvern Callar","pages":481,"published_year":1980},
{"id":39,"author":"Joleen Ilewicz","book_name":"A One-Way Trip to Antibes","pages":498,"published_year":1914},
{"id":40,"author":"Everett Ellerman","book_name":"Irina Palm","pages":314,"published_year":1963},
{"id":41,"author":"Reeba Crowcum","book_name":"Backflash (Backflash Blues)","pages":240,"published_year":1975},
{"id":42,"author":"Sholom Rainey","book_name":"Reluctant Astronaut, The","pages":546,"published_year":1991},
{"id":43,"author":"Gerome O'Lenechan","book_name":"Chicken Run","pages":242,"published_year":2019},
{"id":44,"author":"Alberik Suggate","book_name":"Cavalcade","pages":404,"published_year":1905},
{"id":45,"author":"Hussein Elderkin","book_name":"Two if by Sea","pages":239,"published_year":1970},
{"id":46,"author":"Isaak Cristofvao","book_name":"Look","pages":275,"published_year":1989},
{"id":47,"author":"Marlo True","book_name":"After the Thin Man","pages":520,"published_year":2019},
{"id":48,"author":"Corrianne Leuty","book_name":"Volga - Volga","pages":355,"published_year":1911},
{"id":49,"author":"Mitchael Edess","book_name":"End, The","pages":485,"published_year":1962},
{"id":50,"author":"Shane Blethyn","book_name":"Friends & Lovers","pages":487,"published_year":1937},
{"id":51,"author":"Rici Killcross","book_name":"Carnosaur 2","pages":392,"published_year":2011},
{"id":52,"author":"Ethelyn Wisham","book_name":"Arsenal","pages":508,"published_year":1946},
{"id":53,"author":"Taddeusz Matiashvili","book_name":"Blackadder's Christmas Carol","pages":424,"published_year":1900},
{"id":54,"author":"Gene Ambrosi","book_name":"History of the Eagles","pages":470,"published_year":1901},
{"id":55,"author":"Sheff Maddra","book_name":"Lost in America","pages":287,"published_year":1917},
{"id":56,"author":"Floris Dewey","book_name":"Big Night, The","pages":214,"published_year":1990},
{"id":57,"author":"Irena Rushworth","book_name":"Sudden Manhattan","pages":240,"published_year":1933},
{"id":58,"author":"Delinda Turgoose","book_name":"God told Me To","pages":532,"published_year":1960},
{"id":59,"author":"Marlena Sawyer","book_name":"Arranged","pages":523,"published_year":1972},
{"id":60,"author":"Ginnifer Scrivinor","book_name":"The Skinny","pages":245,"published_year":2007},
{"id":61,"author":"Taffy Chainey","book_name":"Silver Bears","pages":541,"published_year":1978},
{"id":62,"author":"Aretha Matuszyk","book_name":"OMG Oh My God!","pages":584,"published_year":2002},
{"id":63,"author":"Tudor MacNeil","book_name":"Alien Cargo","pages":474,"published_year":1915},
{"id":64,"author":"Brion Billie","book_name":"Man of the World","pages":284,"published_year":1917},
{"id":65,"author":"Jordan Westoll","book_name":"Newest Pledge, The","pages":442,"published_year":1987},
{"id":66,"author":"Loralie O'Flaherty","book_name":"Shall We Kiss? (Un baiser s'il vous plait)","pages":227,"published_year":1998},
{"id":67,"author":"Emily Witts","book_name":"My Wife Is a Gangster (Jopog manura)","pages":484,"published_year":1920},
{"id":68,"author":"Franky Attryde","book_name":"Gabbeh","pages":387,"published_year":1920},
{"id":69,"author":"Miner Dillaway","book_name":"Journey to the Center of the Earth","pages":207,"published_year":1933},
{"id":70,"author":"Simeon Rotham","book_name":"Hero at Large","pages":316,"published_year":1944},
{"id":71,"author":"Christoper Underhill","book_name":"Man from Utah, The","pages":445,"published_year":1953},
{"id":72,"author":"Marleen Cleverley","book_name":"Koi... Mil Gaya","pages":476,"published_year":2010},
{"id":73,"author":"Erina Jee","book_name":"Rude Awakening","pages":507,"published_year":2001},
{"id":74,"author":"Julee Pietranek","book_name":"Aankhen","pages":324,"published_year":2006},
{"id":75,"author":"Eugenia Langridge","book_name":"Black Cat, The","pages":428,"published_year":1925},
{"id":76,"author":"Marilee Dowd","book_name":"Scott of the Antarctic","pages":366,"published_year":1939},
{"id":77,"author":"Timmy Murgatroyd","book_name":"Wild Bees, The (Divoké vcely)","pages":497,"published_year":1976},
{"id":78,"author":"Ethelbert Gillespie","book_name":"My Son the Fanatic","pages":388,"published_year":1964},
{"id":79,"author":"Tanitansy Kunz","book_name":"Blackthorn","pages":231,"published_year":1947},
{"id":80,"author":"Radcliffe Sarson","book_name":"Niko & the Way to the Stars (a.k.a. The Flight Before Christmas) (Niko - Lentäjän poika)","pages":356,"published_year":1980},
{"id":81,"author":"Marinna Dodds","book_name":"Cleaner","pages":489,"published_year":1948},
{"id":82,"author":"Avram Petyankin","book_name":"Last Summer of La Boyita, The (El último verano de la Boyita)","pages":513,"published_year":1917},
{"id":83,"author":"Sheelagh Smallbone","book_name":"Gabrielle","pages":409,"published_year":1927},
{"id":84,"author":"Myrtice Culbard","book_name":"Air Hawks","pages":468,"published_year":1920},
{"id":85,"author":"Carrissa Philippet","book_name":"Blind Sunflowers, The (Los girasoles ciegos)","pages":219,"published_year":2010},
{"id":86,"author":"Ramsey Gallardo","book_name":"Kagemusha","pages":375,"published_year":1927},
{"id":87,"author":"Annabell Rives","book_name":"Wicked Little Things","pages":443,"published_year":1945},
{"id":88,"author":"Janeen Fairholme","book_name":"Snake Eyes","pages":436,"published_year":1950},
{"id":89,"author":"Celka Gooderick","book_name":"Gandhi","pages":529,"published_year":1973},
{"id":90,"author":"Baxie Gwin","book_name":"Riot On!","pages":357,"published_year":1990},
{"id":91,"author":"Kizzie Borit","book_name":"Canon","pages":527,"published_year":1909},
{"id":92,"author":"Dolph Todari","book_name":"Private Lessons (Élève libre)","pages":576,"published_year":1930},
{"id":93,"author":"Deck Porch","book_name":"Thunderbirds Are GO","pages":292,"published_year":1948},
{"id":94,"author":"Harriot Bilsford","book_name":"Four-Faced Liar, The","pages":255,"published_year":2003},
{"id":95,"author":"Dov Garci","book_name":"Love God?, The","pages":424,"published_year":1994},
{"id":96,"author":"Mathe Mattke","book_name":"Saturday the 14th","pages":533,"published_year":2015},
{"id":97,"author":"Clemence Ksandra","book_name":"Zu: Warriors from the Magic Mountain (Xin shu shan jian ke)","pages":440,"published_year":1950},
{"id":98,"author":"Lenora Donnan","book_name":"Gray Matters","pages":453,"published_year":1957},
{"id":99,"author":"Geneva Munton","book_name":"Sea Gull, The","pages":420,"published_year":1972},
{"id":100,"author":"Shell Rimes","book_name":"Four Bags Full","pages":282,"published_year":1908}]